lyberry_dmenu/__init__.py
lyberry_dmenu/__main__.py
lyberry_dmenu/lyberrydmenu.py
lyberry_dmenu-0.0.1.dist-info/LICENSE
lyberry_dmenu-0.0.1.dist-info/METADATA
lyberry_dmenu-0.0.1.dist-info/WHEEL
lyberry_dmenu-0.0.1.dist-info/entry_points.txt
lyberry_dmenu-0.0.1.dist-info/top_level.txt
lyberry_dmenu-0.0.1.dist-info/RECORD
