Metadata-Version: 2.1
Name: lyberry-dmenu
Version: 0.0.1
Summary: A dmenu client for LBRY using lyberry_api
Home-page: https://codeberg.org/vertbyqb/lyberry_dmenu
Author: Vertbyqb
Author-email: vertbyqb@onionmail.org
License: GPLv3+
Platform: UNKNOWN
Classifier: Programming Language :: Python :: 3
Classifier: License :: OSI Approved :: GNU General Public License v3 or later (GPLv3+)
Classifier: Operating System :: OS Independent
Requires-Python: >=3.7
License-File: LICENSE
Requires-Dist: lyberry-api (>=0.1.2)
Requires-Dist: dmenu
